swampy_spatial_datacube/__init__.py
swampy_spatial_datacube/load_config_file.py
swampy_spatial_datacube/masks.py
swampy_spatial_datacube/nc_convert.py
swampy_spatial_datacube/pbs_job_setup.py
swampy_spatial_datacube/query_datacube.py
swampy_spatial_datacube/sam_com_multi_process.py
swampy_spatial_datacube/swampy_datacube_plotting.py
swampy_spatial_datacube/swampy_spatial_datacube.py
swampy_spatial_datacube-1.1.4.dist-info/DESCRIPTION.rst
swampy_spatial_datacube-1.1.4.dist-info/METADATA
swampy_spatial_datacube-1.1.4.dist-info/RECORD
swampy_spatial_datacube-1.1.4.dist-info/WHEEL
swampy_spatial_datacube-1.1.4.dist-info/entry_points.txt
swampy_spatial_datacube-1.1.4.dist-info/metadata.json
swampy_spatial_datacube-1.1.4.dist-info/top_level.txt
