Metadata-Version: 2.0
Name: swampy-spatial-datacube
Version: 1.1.4
Summary: swampy_spatial_datacube
Home-page: UNKNOWN
Author: Mike Caccetta
Author-email: mike.caccetta@csiro.au
License: Unknown
Keywords: Hydrology Modeling Bathymetry
Platform: any
Classifier: Development Status :: 3 - Alpha
Classifier: Intended Audience :: Science/Research
Classifier: Programming Language :: Python :: 3
Requires-Dist: datacube (>=1.5.1)
Requires-Dist: s-swampy (>=0.2.2)
